MANIFEST.in
README
betsy
mangler.py
setup.cfg
setup.py
test/__init__.py
test/__init__.pyc
test/test_compile.py
test/__pycache__/test_compile.cpython-27-PYTEST.pyc
tiddlywebplugins/__init__.py
tiddlywebplugins.hoster.egg-info/PKG-INFO
tiddlywebplugins.hoster.egg-info/SOURCES.txt
tiddlywebplugins.hoster.egg-info/dependency_links.txt
tiddlywebplugins.hoster.egg-info/namespace_packages.txt
tiddlywebplugins.hoster.egg-info/not-zip-safe
tiddlywebplugins.hoster.egg-info/pbr.json
tiddlywebplugins.hoster.egg-info/requires.txt
tiddlywebplugins.hoster.egg-info/top_level.txt
tiddlywebplugins/hoster/__init__.py
tiddlywebplugins/hoster/config.py
tiddlywebplugins/hoster/data.py
tiddlywebplugins/hoster/extractor.py
tiddlywebplugins/hoster/instance.py
tiddlywebplugins/hoster/serialization.py
tiddlywebplugins/hoster/template.py
tiddlywebplugins/hoster/resources/store/bags/help/description
tiddlywebplugins/hoster/resources/store/bags/help/policy
tiddlywebplugins/hoster/resources/store/bags/help/tiddlers/WorkspaceConfig/1
tiddlywebplugins/hoster/resources/store/bags/hoster/description
tiddlywebplugins/hoster/resources/store/bags/hoster/policy
tiddlywebplugins/hoster/resources/store/bags/hoster/tiddlers/bagdesc.js/1
tiddlywebplugins/hoster/resources/store/bags/hoster/tiddlers/bagmanage.js/1
tiddlywebplugins/hoster/resources/store/bags/hoster/tiddlers/cat.png/1
tiddlywebplugins/hoster/resources/store/bags/hoster/tiddlers/cats.jpg/1
tiddlywebplugins/hoster/resources/store/bags/hoster/tiddlers/credits/1
tiddlywebplugins/hoster/resources/store/bags/hoster/tiddlers/delete.png/1
tiddlywebplugins/hoster/resources/store/bags/hoster/tiddlers/drop.js/1
tiddlywebplugins/hoster/resources/store/bags/hoster/tiddlers/generaterecipe.js/1
tiddlywebplugins/hoster/resources/store/bags/hoster/tiddlers/json2.js/1
tiddlywebplugins/hoster/resources/store/bags/hoster/tiddlers/main.css/1
tiddlywebplugins/hoster/resources/store/bags/hoster/tiddlers/pencil.png/1
tiddlywebplugins/hoster/resources/store/bags/hoster/tiddlers/picture_add.png/1
tiddlywebplugins/hoster/resources/store/bags/hoster/tiddlers/recipemanage.js/1
tiddlywebplugins/hoster/resources/store/bags/hoster/tiddlers/templater.js/1
tiddlywebplugins/hoster/resources/store/bags/hoster/tiddlers/ui-bg_flat_0_aaaaaa_40x100.png/1
tiddlywebplugins/hoster/resources/store/bags/hoster/tiddlers/ui-bg_flat_75_ffffff_40x100.png/1
