Metadata-Version: 1.0
Name: tiddlywebplugins.hoster
Version: 0.9.51
Summary: A hoster for TiddlyWikis
Home-page: http://pypi.python.org/pypi/tiddlywebplugins.hoster
Author: Chris Dent
Author-email: cdent@peermore.com
License: UNKNOWN
Platform: Posix; MacOS X; Windows
